ros2_geek/__init__.py
ros2_geek/async_tools.py
ros2_geek/client_manager.py
ros2_geek/controller_manager_tools.py
ros2_geek/launch_manager.py
ros2_geek/metaclasses.py
ros2_geek/moveit_interface.py
ros2_geek/node_pro.py
ros2_geek/topic_manager.py
ros2_geek/utils.py
ros2_geek-0.2.0.dist-info/METADATA
ros2_geek-0.2.0.dist-info/WHEEL
ros2_geek-0.2.0.dist-info/top_level.txt
ros2_geek-0.2.0.dist-info/RECORD
