Metadata-Version: 2.1
Name: ros2-geek
Version: 0.2.0
Summary: ROS2 Geek
Author-email: OpenGHz <your.email@example.com>
License: MIT
Requires-Python: >=3.8
Requires-Dist: pydantic
Requires-Dist: numpy
Provides-Extra: all
Provides-Extra: cv2
Requires-Dist: opencv-python; extra == "cv2"
